classy_vision/__init__.py
classy_vision/dataset/__init__.py
classy_vision/dataset/classy_cifar.py
classy_vision/dataset/classy_dataset.py
classy_vision/dataset/classy_hmdb51.py
classy_vision/dataset/classy_kinetics400.py
classy_vision/dataset/classy_synthetic_image.py
classy_vision/dataset/classy_synthetic_image_streaming.py
classy_vision/dataset/classy_synthetic_video.py
classy_vision/dataset/classy_ucf101.py
classy_vision/dataset/classy_video_dataset.py
classy_vision/dataset/dataloader_async_gpu_wrapper.py
classy_vision/dataset/dataloader_limit_wrapper.py
classy_vision/dataset/dataloader_skip_none_wrapper.py
classy_vision/dataset/dataloader_wrapper.py
classy_vision/dataset/image_path_dataset.py
classy_vision/dataset/core/__init__.py
classy_vision/dataset/core/list_dataset.py
classy_vision/dataset/core/random_image_datasets.py
classy_vision/dataset/core/random_video_datasets.py
classy_vision/dataset/transforms/__init__.py
classy_vision/dataset/transforms/autoaugment.py
classy_vision/dataset/transforms/classy_transform.py
classy_vision/dataset/transforms/lighting_transform.py
classy_vision/dataset/transforms/mixup.py
classy_vision/dataset/transforms/util.py
classy_vision/dataset/transforms/util_video.py
classy_vision/distributed/__init__.py
classy_vision/distributed/launch_ray.py
classy_vision/generic/__init__.py
classy_vision/generic/debug.py
classy_vision/generic/distributed_util.py
classy_vision/generic/opts.py
classy_vision/generic/pdb.py
classy_vision/generic/perf_stats.py
classy_vision/generic/profiler.py
classy_vision/generic/registry_utils.py
classy_vision/generic/util.py
classy_vision/generic/visualize.py
classy_vision/heads/__init__.py
classy_vision/heads/classy_head.py
classy_vision/heads/fully_connected_head.py
classy_vision/heads/fully_convolutional_linear_head.py
classy_vision/heads/identity_head.py
classy_vision/heads/vision_transformer_head.py
classy_vision/hooks/__init__.py
classy_vision/hooks/checkpoint_hook.py
classy_vision/hooks/classy_hook.py
vissl-0.1.6.dist-info/LICENSE
vissl-0.1.6.dist-info/METADATA
vissl-0.1.6.dist-info/NOTICE
vissl-0.1.6.dist-info/WHEEL
vissl-0.1.6.dist-info/top_level.txt
vissl-0.1.6.dist-info/RECORD
