Metadata-Version: 2.1
Name: vissl
Version: 0.1.6
Summary: VISSL is an extensible, modular and scalable library for SOTA Self-Supervised Learning with images.
Home-page: https://github.com/facebookresearch/vissl
Author: Facebook AI Research
Author-email: vissl@fb.com
License: MIT
Platform: UNKNOWN
Requires-Python: >=3.6.2
License-File: LICENSE
License-File: NOTICE
Requires-Dist: cython (==0.29.22)
Requires-Dist: fvcore (==0.1.3.post20210317)
Requires-Dist: iopath (==0.1.9)
Requires-Dist: hydra-core (==1.0.7)
Requires-Dist: numpy (==1.19.5)
Requires-Dist: parameterized (==0.7.4)
Requires-Dist: scikit-learn (==0.24.1)
Requires-Dist: submitit (==1.3.3)
Requires-Dist: tabulate (==0.8.9)
Provides-Extra: dev
Requires-Dist: black (==19.3b0) ; extra == 'dev'
Requires-Dist: sphinx ; extra == 'dev'
Requires-Dist: isort (==5.7.0) ; extra == 'dev'
Requires-Dist: flake8 (==3.8.1) ; extra == 'dev'
Requires-Dist: flake8-bugbear ; extra == 'dev'
Requires-Dist: flake8-comprehensions ; extra == 'dev'
Requires-Dist: pre-commit ; extra == 'dev'
Requires-Dist: nbconvert ; extra == 'dev'
Requires-Dist: bs4 ; extra == 'dev'
Requires-Dist: faiss-gpu ; extra == 'dev'
Requires-Dist: pycocotools (>=2.0.1) ; extra == 'dev'
Requires-Dist: tensorboard (>=1.15) ; extra == 'dev'
